plot_highlight/__init__.py
plot_highlight/highlightplot.py
plot_highlight-0.1.0.dist-info/LICENSE
plot_highlight-0.1.0.dist-info/METADATA
plot_highlight-0.1.0.dist-info/WHEEL
plot_highlight-0.1.0.dist-info/top_level.txt
plot_highlight-0.1.0.dist-info/RECORD
