Metadata-Version: 2.1
Name: plot_highlight
Version: 0.1.0
Summary: plot_highlight is a Python visualization library based on seaborn.
Author-email: SHIRO <shiro46mt@gmail.com>
License: MIT License
Project-URL: Repository, https://github.com/shiro46mt/plot-highlight.git
Classifier: Development Status :: 4 - Beta
Classifier: Framework :: Matplotlib
Classifier: Programming Language :: Python :: 3
Classifier: Topic :: Multimedia :: Graphics
Classifier: Topic :: Scientific/Engineering :: Visualization
Requires-Python: >=3.8
License-File: LICENSE
Requires-Dist: matplotlib
Requires-Dist: seaborn
